{
        "ListenAddress":"tcp://0.0.0.0:1883",
        "UserName":"homekit",
        "Password":"homekit",
        "name":"homekitbridge",
        "serialNumber":"a0FAE167558F",
        "manufacturer":"HB",
        "Model":"Homkit",
        "Pin":"98100661",
        "AccessoryList":[
                {
                        "metric":"sht3x_temperature",
                        "metricEndpoint":"http://10.0.1.3:9090",
                        "name":"bedTemp",
                        "serialNumber":"a0FAE167558F",
                        "manufacturer":"HB",
                        "Model":"Temperature",
                        "accessoryType":"TemperatureSensor"
                },
                {
                        "metric":"sht3x_humidity",
                        "metricEndpoint":"http://10.0.1.3:9090",
                        "name":"bedHumidity",
                        "serialNumber":"aEFAE167559F",
                        "manufacturer":"HB",
                        "Model":"Humidity",
                        "accessoryType":"HumiditySensor"
                },
                {
                        "metric":"mhz19b_co2_ppm",
                        "metricEndpoint":"http://10.0.1.3:9090",
                        "name":"CarbonDioxideSensor",
                        "serialNumber":"ADFGE167561D",
                        "manufacturer":"HB",
                        "Model":"AirQualityCO2",
                        "accessoryType":"CarbonDioxideSensor"
                }
        ]
}
